LICENSE
README.md
siftlog/__init__.py
siftlog/tests/__init__.py
siftlog/tests/test_json_color.py
siftlog/tests/test_log.py
siftlog/tests/test_plain_color.py
siftlog_py-0.9.5.dist-info/METADATA
siftlog_py-0.9.5.dist-info/WHEEL
siftlog_py-0.9.5.dist-info/LICENSE
siftlog_py-0.9.5.dist-info/RECORD
