Metadata-Version: 2.1
Name: siftlog-py
Version: 0.9.5
Summary: JSON and human-readable logging with context
Home-page: https://github.com/papito/siftlog-py
License: MIT
Keywords: logging,logs,structured
Author: Andrei Taranchenko
Author-email: drey10@gmail.com
Requires-Python: >=3.8,<4.0
Classifier: License :: OSI Approved :: MIT License
Classifier: Programming Language :: Python :: 3
Classifier: Programming Language :: Python :: 3.8
Classifier: Programming Language :: Python :: 3.9
Classifier: Programming Language :: Python :: 3.10
Classifier: Programming Language :: Python :: 3.11
Project-URL: Repository, https://github.com/papito/siftlog-py
